disclist/__init__.py
disclist/client.py
disclist/errors.py
disclist-0.0.2.dist-info/LICENSE
disclist-0.0.2.dist-info/WHEEL
disclist-0.0.2.dist-info/METADATA
disclist-0.0.2.dist-info/RECORD
