Metadata-Version: 2.1
Name: disclist
Version: 0.0.2
Summary: A simple asynchronous/synchronous wrapper for https://disclist.noxitb.repl.co/ Bot List.
License: MIT
Author: proguy914629
Requires-Python: >=3.5
Classifier: License :: OSI Approved :: MIT License
Classifier: Programming Language :: Python :: 3
Classifier: Programming Language :: Python :: 3.5
Classifier: Programming Language :: Python :: 3.6
Classifier: Programming Language :: Python :: 3.7
Classifier: Programming Language :: Python :: 3.8
Classifier: Programming Language :: Python :: 3.9
Requires-Dist: aiohttp (>=3.7.4,<4.0.0)
Requires-Dist: requests (>=2.25.1,<3.0.0)
